[
  {
    "id": "oboi_001",
    "category": "oboi",
    "active": true,
    "name_ru": "Жидкие обои Classic 203",
    "name_lv": "Šķidrās tapetes Classic 203",
    "name_en": "Liquid wallpaper Classic 203",
    "price_eur": 49,
    "image": "liquid_wallpaper_classic_203.jpg",
    "desc_ru": "Мягкая фактура, хорошо скрывает мелкие неровности. Расход: ~3.5 м²/уп.",
    "desc_lv": "Mīksta faktūra, labi noslēpj nelielus defektus. Patēriņš: ~3.5 m²/iep.",
    "desc_en": "Soft texture, hides minor defects. Coverage: ~3.5 m²/pack."
  },
  {
    "id": "oboi_002",
    "category": "oboi",
    "active": true,
    "name_ru": "Жидкие обои Premium 510",
    "name_lv": "Šķidrās tapetes Premium 510",
    "name_en": "Liquid wallpaper Premium 510",
    "price_eur": 59,
    "image": "IMG_0900.jpeg",
    "desc_ru": "Премиум-серия, плотнее слой, эффектнее фактура.",
    "desc_lv": "Premium sērija, biezāks slānis, izteiksmīgāka faktūra.",
    "desc_en": "Premium series, thicker layer, more expressive texture."
  }
]
